oesnn_ad/__init__.py
oesnn_ad/grf_init.py
oesnn_ad/layer.py
oesnn_ad/neuron.py
oesnn_ad/oesnn_ad.py
oesnn_ad/decompose/__init__.py
oesnn_ad/decompose/committee_decompose.py
oesnn_ad/decompose/decompose.py
oesnn_ad/decompose/weighted_decompose.py
tests/__init__.py
tests/test_grf_init.py
tests/test_layers.py
tests/test_neuron.py
tests/test_oesnn_ad.py
tests/test_decompose/__init__.py
tests/test_decompose/test_commite_decompose.py
tests/test_decompose/test_decompose.py
tests/test_decompose/test_weighted_decompose.py
OeSNN_AD-1.0.1.dist-info/LICENSE
OeSNN_AD-1.0.1.dist-info/METADATA
OeSNN_AD-1.0.1.dist-info/WHEEL
OeSNN_AD-1.0.1.dist-info/top_level.txt
OeSNN_AD-1.0.1.dist-info/RECORD
