Metadata-Version: 2.1
Name: OeSNN-AD
Version: 1.0.1
Summary: OeSNN-UAD anomaly detector implementation for Python.
Author: Mariusz Paluch
Author-email: mariuszpaluch001@gmail.com
Keywords: python,data stream,spiking neural network,SNN,anomalies,anomaly detection,CEEMDAN
Classifier: Development Status :: 5 - Production/Stable
Classifier: Intended Audience :: Developers
Classifier: Intended Audience :: Science/Research
Classifier: Programming Language :: Python :: 3
Classifier: Operating System :: Unix
Classifier: Operating System :: MacOS :: MacOS X
Classifier: Operating System :: Microsoft :: Windows
License-File: LICENSE
Requires-Dist: numpy
Requires-Dist: EMD-signal
